where/cli.py
where/exceptions.py
where/finder.py
where/utils.py
gbwhere-0.1.3.dist-info/METADATA
gbwhere-0.1.3.dist-info/WHEEL
gbwhere-0.1.3.dist-info/entry_points.txt
gbwhere-0.1.3.dist-info/RECORD
