Metadata-Version: 2.1
Name: gbwhere
Version: 0.1.3
Summary: 
Author: rdsgabriel
Author-email: rdsgabriel.dev@gmail.com
Requires-Python: >=3.10,<4.0
Classifier: Programming Language :: Python :: 3
Classifier: Programming Language :: Python :: 3.10
Classifier: Programming Language :: Python :: 3.11
Requires-Dist: click (>=8.1.3,<9.0.0)
Requires-Dist: tabulate (>=0.9.0,<0.10.0)
